Pop_Exp/__init__.py
Pop_Exp/find_exposure.py
pop_exp-0.1.9.dist-info/LICENSE
pop_exp-0.1.9.dist-info/METADATA
pop_exp-0.1.9.dist-info/WHEEL
pop_exp-0.1.9.dist-info/RECORD
