Metadata-Version: 2.3
Name: Pop_Exp
Version: 0.1.9
Summary: A package for finding the number of people residing near environmental hazards
License: MIT
Keywords: population,exposure,wildfires,environmental hazards,climate hazards,find people exposed
Author: heathermcb
Author-email: heathermcbrien2.0@gmail.com
Requires-Python: >=3.12
Classifier: Programming Language :: Python :: 3
Classifier: Operating System :: OS Independent
Classifier: License :: OSI Approved :: MIT License
Classifier: Development Status :: 4 - Beta
Classifier: Intended Audience :: Developers
Classifier: Topic :: Software Development :: Libraries :: Python Modules
Requires-Dist: affine
Requires-Dist: exactextract
Requires-Dist: geopandas (==1.0.1)
Requires-Dist: matplotlib
Requires-Dist: mkdocs
Requires-Dist: numpy (==2.0.1)
Requires-Dist: pandas
Requires-Dist: pathlib
Requires-Dist: pre-commit
Requires-Dist: pyarrow
Requires-Dist: rasterio
Requires-Dist: scipy (==1.14.0)
Requires-Dist: shapely
Requires-Dist: tqdm
Requires-Dist: typing
Project-URL: Documentation, https://github.com/heathermcb/Pop_Exp#readme
Project-URL: Homepage, https://github.com/heathermcb/Pop_Exp
Project-URL: Source, https://github.com/heathermcb/Pop_Exp
